ydata_quality/__init__.py
ydata_quality/__version__.py
ydata_quality/bias_fairness/__init__.py
ydata_quality/bias_fairness/engine.py
ydata_quality/core/__init__.py
ydata_quality/core/data_quality.py
ydata_quality/core/engine.py
ydata_quality/core/warnings.py
ydata_quality/data_expectations/__init__.py
ydata_quality/data_expectations/engine.py
ydata_quality/data_relations/__init__.py
ydata_quality/data_relations/engine.py
ydata_quality/drift/__init__.py
ydata_quality/drift/engine.py
ydata_quality/duplicates/__init__.py
ydata_quality/duplicates/engine.py
ydata_quality/erroneous_data/__init__.py
ydata_quality/erroneous_data/engine.py
ydata_quality/labelling/__init__.py
ydata_quality/labelling/engine.py
ydata_quality/missings/__init__.py
ydata_quality/missings/engine.py
ydata_quality/utils/__init__.py
ydata_quality/utils/auxiliary.py
ydata_quality/utils/correlations.py
ydata_quality/utils/enum.py
ydata_quality/utils/logger.py
ydata_quality/utils/modelling.py
ydata_quality-0.1.0.dist-info/LICENSE
ydata_quality-0.1.0.dist-info/METADATA
ydata_quality-0.1.0.dist-info/WHEEL
ydata_quality-0.1.0.dist-info/top_level.txt
ydata_quality-0.1.0.dist-info/RECORD
