Metadata-Version: 2.1
Name: ydata-quality
Version: 0.1.0
Summary: YData open-source tools for Data Quality.
Home-page: https://github.com/ydataai/ydata-quality
Author: YData
Author-email: community@ydata.ai
License: https://github.com/ydataai/ydata-quality/blob/master/LICENSE
Keywords: data science ydata
Platform: UNKNOWN
Classifier: Development Status :: 3 - Alpha
Classifier: Intended Audience :: Developers
Classifier: Intended Audience :: Education
Classifier: Intended Audience :: End Users/Desktop
Classifier: Intended Audience :: Financial and Insurance Industry
Classifier: Intended Audience :: Healthcare Industry
Classifier: Intended Audience :: Science/Research
Classifier: Intended Audience :: Telecommunications Industry
Classifier: License :: OSI Approved :: GNU General Public License v3 or later (GPLv3+)
Classifier: Operating System :: POSIX :: Linux
Classifier: Operating System :: MacOS
Classifier: Operating System :: Microsoft :: Windows
Classifier: Programming Language :: Python :: 3 :: Only
Classifier: Programming Language :: Python :: Implementation
Classifier: Topic :: Scientific/Engineering :: Artificial Intelligence
Classifier: Topic :: Software Development
Classifier: Topic :: Software Development :: Libraries :: Python Modules
Requires-Python: >=3.6, <3.9
Requires-Dist: dython (==0.6.7)
Requires-Dist: matplotlib (==3.4.2)
Requires-Dist: numpy (==1.20.3)
Requires-Dist: pandas (==1.2.*)
Requires-Dist: pydantic (==1.8.2)
Requires-Dist: scikit-learn (==0.24.2)
Requires-Dist: statsmodels (==0.12.2)
